{
	"companySharesInformation": [
		{
			"companySymbol": "TCS",
			"companyName": "Tata Consultancy Service",
			"companyShares": 121,
			"companySharePrices": 7835,
			"companyTotalSharePriceValue": 948035
		},
		{
			"companySymbol": "MSFT",
			"companyName": "Microsoft",
			"companyShares": 451,
			"companySharePrices": 3654,
			"companyTotalSharePriceValue": 1647954
		},
		{
			"companySymbol": "JSW",
			"companyName": "Jindal South West",
			"companyShares": 680,
			"companySharePrices": 7345,
			"companyTotalSharePriceValue": 4994600
		},
		{
			"companySymbol": "IBM",
			"companyName": "International Bussiness Machines",
			"companyShares": 229,
			"companySharePrices": 3635,
			"companyTotalSharePriceValue": 832415
		}
	]
}